[{"id":24,"expected":"Safe","received":"Safe"},{"id":714,"expected":"Vulnerable","received":"Safe"},{"id":354,"expected":"Safe","received":"Vulnerable"},{"id":496,"expected":"Vulnerable","received":"Vulnerable"},{"id":20,"expected":"Safe","received":"Safe"},{"id":254,"expected":"Safe","received":"Safe"},{"id":674,"expected":"Vulnerable","received":"Vulnerable"},{"id":309,"expected":"Safe","received":"Vulnerable"},{"id":401,"expected":"Safe","received":"Safe"},{"id":704,"expected":"Vulnerable","received":"Vulnerable"},{"id":256,"expected":"Safe","received":"Safe"},{"id":433,"expected":"Vulnerable","received":"Safe"},{"id":50,"expected":"Safe","received":"Safe"},{"id":655,"expected":"Vulnerable","received":"Vulnerable"},{"id":583,"expected":"Vulnerable","received":"Vulnerable"},{"id":333,"expected":"Safe","received":"Vulnerable"},{"id":473,"expected":"Vulnerable","received":"Safe"},{"id":693,"expected":"Vulnerable","received":"Vulnerable"},{"id":82,"expected":"Safe","received":"Safe"},{"id":98,"expected":"Safe","received":"Safe"},{"id":200,"expected":"Safe","received":"Safe"},{"id":70,"expected":"Safe","received":"Safe"},{"id":367,"expected":"Safe","received":"Safe"},{"id":127,"expected":"Safe","received":"Safe"},{"id":690,"expected":"Vulnerable","received":"Vulnerable"},{"id":350,"expected":"Safe","received":"Safe"},{"id":758,"expected":"Vulnerable","received":"Vulnerable"},{"id":64,"expected":"Safe","received":"Safe"},{"id":91,"expected":"Safe","received":"Safe"},{"id":26,"expected":"Safe","received":"Safe"},{"id":520,"expected":"Vulnerable","received":"31 PMSample 1"},{"id":84,"expected":"Safe","received":"Vulnerable"},{"id":593,"expected":"Vulnerable","received":"Vulnerable"},{"id":59,"expected":"Safe","received":"Safe"},{"id":670,"expected":"Vulnerable","received":"Safe"},{"id":302,"expected":"Safe","received":"Safe"},{"id":458,"expected":"Vulnerable","received":"Safe"},{"id":5,"expected":"Safe","received":"Safe"},{"id":677,"expected":"Vulnerable","received":"Safe"},{"id":531,"expected":"Vulnerable","received":"Vulnerable"},{"id":218,"expected":"Safe","received":"Safe"},{"id":718,"expected":"Vulnerable","received":"Vulnerable"},{"id":115,"expected":"Safe","received":"Safe"},{"id":547,"expected":"Vulnerable","received":"Safe"},{"id":222,"expected":"Safe","received":"Safe"},{"id":421,"expected":"Vulnerable","received":"Vulnerable"},{"id":4,"expected":"Safe","received":"Safe"},{"id":56,"expected":"Safe","received":"Safe"},{"id":529,"expected":"Vulnerable","received":"Vulnerable"},{"id":607,"expected":"Vulnerable","received":"Safe"},{"id":101,"expected":"Safe","received":"Safe"},{"id":97,"expected":"Safe","received":"Vulnerable"},{"id":544,"expected":"Vulnerable","received":"Safe"},{"id":408,"expected":"Vulnerable","received":"Vulnerable"},{"id":251,"expected":"Safe","received":"Safe"},{"id":255,"expected":"Safe","received":"Safe"},{"id":219,"expected":"Safe","received":"Safe"},{"id":745,"expected":"Vulnerable","received":"Vulnerable"},{"id":81,"expected":"Safe","received":"Safe"},{"id":292,"expected":"Safe","received":"Safe"},{"id":31,"expected":"Safe","received":"Safe"},{"id":767,"expected":"Vulnerable","received":"Vulnerable"},{"id":435,"expected":"Vulnerable","received":"Safe"},{"id":785,"expected":"Vulnerable","received":"Vulnerable"},{"id":356,"expected":"Safe","received":"Safe"},{"id":707,"expected":"Vulnerable","received":"Safe"},{"id":641,"expected":"Vulnerable","received":"Vulnerable"},{"id":739,"expected":"Vulnerable","received":"Vulnerable"},{"id":294,"expected":"Safe","received":"Safe"},{"id":789,"expected":"Vulnerable","received":"Safe"},{"id":554,"expected":"Vulnerable","received":"Vulnerable"},{"id":279,"expected":"Safe","received":"Vulnerable"},{"id":217,"expected":"Safe","received":"Safe"},{"id":638,"expected":"Vulnerable","received":"Safe"},{"id":335,"expected":"Safe","received":"Vulnerable"},{"id":315,"expected":"Safe","received":"Vulnerable"},{"id":399,"expected":"Safe","received":"Vulnerable"},{"id":52,"expected":"Safe","received":"Vulnerable"},{"id":18,"expected":"Safe","received":"Vulnerable"},{"id":610,"expected":"Vulnerable","received":"Vulnerable"},{"id":46,"expected":"Safe","received":"Safe"},{"id":515,"expected":"Vulnerable","received":"Safe"},{"id":548,"expected":"Vulnerable","received":"Vulnerable"},{"id":577,"expected":"Vulnerable","received":"Vulnerable"},{"id":38,"expected":"Safe","received":"Safe"},{"id":215,"expected":"Safe","received":"Safe"},{"id":381,"expected":"Safe","received":"Safe"},{"id":558,"expected":"Vulnerable","received":"Safe"},{"id":727,"expected":"Vulnerable","received":"Safe"},{"id":275,"expected":"Safe","received":"Safe"},{"id":474,"expected":"Vulnerable","received":"Vulnerable"},{"id":132,"expected":"Safe","received":"Safe"},{"id":626,"expected":"Vulnerable","received":"Vulnerable"},{"id":628,"expected":"Vulnerable","received":"Safe"},{"id":728,"expected":"Vulnerable","received":"Safe"},{"id":304,"expected":"Safe","received":"Safe"},{"id":67,"expected":"Safe","received":"Safe"},{"id":749,"expected":"Vulnerable","received":"Safe"},{"id":578,"expected":"Vulnerable","received":"Safe"},{"id":501,"expected":"Vulnerable","received":"Vulnerable"},{"id":271,"expected":"Safe","received":"Safe"},{"id":726,"expected":"Vulnerable","received":"Safe"},{"id":400,"expected":"Safe","received":"Safe"},{"id":695,"expected":"Vulnerable","received":"Vulnerable"},{"id":135,"expected":"Safe","received":"Safe"},{"id":320,"expected":"Safe","received":"Vulnerable"},{"id":77,"expected":"Safe","received":"Safe"},{"id":202,"expected":"Safe","received":"Safe"},{"id":770,"expected":"Vulnerable","received":"Safe"},{"id":60,"expected":"Safe","received":"Safe"},{"id":227,"expected":"Safe","received":"Safe"},{"id":402,"expected":"Safe","received":"Safe"},{"id":720,"expected":"Vulnerable","received":"Vulnerable"},{"id":331,"expected":"Safe","received":"Safe"},{"id":53,"expected":"Safe","received":"Safe"},{"id":186,"expected":"Safe","received":"Safe"},{"id":661,"expected":"Vulnerable","received":"Vulnerable"},{"id":276,"expected":"Safe","received":"Safe"},{"id":477,"expected":"Vulnerable","received":"Safe"},{"id":567,"expected":"Vulnerable","received":"Safe"},{"id":75,"expected":"Safe","received":"Vulnerable"},{"id":345,"expected":"Safe","received":"Safe"},{"id":206,"expected":"Safe","received":"Safe"},{"id":418,"expected":"Vulnerable","received":"Vulnerable"},{"id":456,"expected":"Vulnerable","received":"Safe"},{"id":90,"expected":"Safe","received":"Vulnerable"},{"id":484,"expected":"Vulnerable","received":"Safe"},{"id":649,"expected":"Vulnerable","received":"Safe"},{"id":8,"expected":"Safe","received":"Safe"},{"id":87,"expected":"Safe","received":"Safe"},{"id":49,"expected":"Vulnerable","received":"Safe"},{"id":35,"expected":"Safe","received":"Safe"},{"id":165,"expected":"Safe","received":"Safe"},{"id":192,"expected":"Safe","received":"Safe"},{"id":561,"expected":"Vulnerable","received":"Safe"},{"id":581,"expected":"Vulnerable","received":"Safe"},{"id":266,"expected":"Safe","received":"Safe"},{"id":796,"expected":"Vulnerable","received":"Vulnerable"},{"id":125,"expected":"Safe","received":"Safe"},{"id":555,"expected":"Vulnerable","received":"Vulnerable"},{"id":29,"expected":"Safe","received":"Safe"},{"id":441,"expected":"Vulnerable","received":"Vulnerable"},{"id":382,"expected":"Safe","received":"Safe"},{"id":573,"expected":"Vulnerable","received":"Safe"},{"id":528,"expected":"Vulnerable","received":"Vulnerable"},{"id":105,"expected":"Safe","received":"Safe"},{"id":12,"expected":"Safe","received":"Safe"},{"id":150,"expected":"Safe","received":"Safe"},{"id":631,"expected":"Vulnerable","received":"Vulnerable"},{"id":2,"expected":"Vulnerable","received":"Safe"},{"id":351,"expected":"Safe","received":"Safe"},{"id":685,"expected":"Vulnerable","received":"Vulnerable"},{"id":112,"expected":"Safe","received":"Safe"},{"id":428,"expected":"Vulnerable","received":"Vulnerable"},{"id":771,"expected":"Vulnerable","received":"Vulnerable"},{"id":131,"expected":"Safe","received":"Safe"},{"id":526,"expected":"Vulnerable","received":"Safe"},{"id":521,"expected":"Vulnerable","received":"Safe"},{"id":117,"expected":"Safe","received":"Safe"},{"id":278,"expected":"Safe","received":"Safe"},{"id":316,"expected":"Safe","received":"Safe"},{"id":754,"expected":"Vulnerable","received":"Safe"},{"id":370,"expected":"Safe","received":"Safe"},{"id":119,"expected":"Safe","received":"Safe"},{"id":86,"expected":"Safe","received":"Safe"},{"id":40,"expected":"Safe","received":"Safe"},{"id":594,"expected":"Vulnerable","received":"Vulnerable"},{"id":595,"expected":"Vulnerable","received":"Vulnerable"},{"id":542,"expected":"Vulnerable","received":"Safe"},{"id":143,"expected":"Safe","received":"Vulnerable"},{"id":396,"expected":"Safe","received":"Safe"},{"id":225,"expected":"Safe","received":"Vulnerable"},{"id":634,"expected":"Vulnerable","received":"Vulnerable"},{"id":462,"expected":"Vulnerable","received":"Safe"},{"id":296,"expected":"Safe","received":"Safe"}]